bzutils/LogUtil.py
bzutils/__init__.py
bzutil-1.0.8.dist-info/LICENSE
bzutil-1.0.8.dist-info/METADATA
bzutil-1.0.8.dist-info/WHEEL
bzutil-1.0.8.dist-info/top_level.txt
bzutil-1.0.8.dist-info/RECORD
